{"type":"FeatureCollection","features":[{"id":"13","type":"Feature","properties":{"name":"NDBC Buoy Station 63112"},"geometry":{"type":"Point","coordinates":[0,8649511.97660112]}},{"id":"157","type":"Feature","properties":{"name":"NDBC Buoy Station 62304"},"geometry":{"type":"Point","coordinates":[200375.083427891,6639533.49330808]}},{"id":"159","type":"Feature","properties":{"name":"NDBC Buoy Station 63113"},"geometry":{"type":"Point","coordinates":[189243.134348565,8625823.20020359]}},{"id":"237","type":"Feature","properties":{"name":"NDBC Buoy Station 62142"},"geometry":{"type":"Point","coordinates":[233882.250156669,6982997.92038979]}},{"id":"351","type":"Feature","properties":{"name":"NDBC Buoy Station 97001"},"geometry":{"type":"Point","coordinates":[6138156.7223411,635570.339317788]}},{"id":"407","type":"Feature","properties":{"name":"NDBC Buoy Station 62165"},"geometry":{"type":"Point","coordinates":[122451.439872602,7170156.29399995]}},{"id":"396","type":"Feature","properties":{"name":"NDBC Buoy Station 61002"},"geometry":{"type":"Point","coordinates":[523535.565200765,5176270.81624419]}},{"id":"489","type":"Feature","properties":{"name":"NDBC Buoy Station 63110"},"geometry":{"type":"Point","coordinates":[166979.236189911,8289249.92658655]}},{"id":"527","type":"Feature","properties":{"name":"NDBC Buoy Station 62114"},"geometry":{"type":"Point","coordinates":[11131.9490793267,8030603.97827452]}},{"id":"523","type":"Feature","properties":{"name":"NDBC Buoy Station 62305"},"geometry":{"type":"Point","coordinates":[0,6515839.14761188]}},{"id":"597","type":"Feature","properties":{"name":"NDBC Buoy Station 62164"},"geometry":{"type":"Point","coordinates":[55659.7453966362,7801312.7787566]}},{"id":"637","type":"Feature","properties":{"name":"NDBC Buoy Station 62146"},"geometry":{"type":"Point","coordinates":[311694.574221166,7132369.31229549]}}]}