{"type":"FeatureCollection","features":[{"id":"46","type":"Feature","properties":{"name":"NDBC Buoy Station 45027"},"geometry":{"type":"Point","coordinates":[-10233489.4691348,5919903.59480726]}},{"id":"36","type":"Feature","properties":{"name":"NDBC Buoy Station GDMM5"},"geometry":{"type":"Point","coordinates":[-10056825.4372459,6065032.94069515]}},{"id":"114","type":"Feature","properties":{"name":"NDBC Buoy Station SXHW3"},"geometry":{"type":"Point","coordinates":[-10067734.7473437,5871033.98823632]}},{"id":"163","type":"Feature","properties":{"name":"NDBC Buoy Station SLVM5"},"geometry":{"type":"Point","coordinates":[-10158126.1738678,5986092.78478966]}},{"id":"189","type":"Feature","properties":{"name":"NDBC Buoy Station DULM5"},"geometry":{"type":"Point","coordinates":[-10251745.8656249,5905425.36470945]}},{"id":"546","type":"Feature","properties":{"name":"NDBC Buoy Station DISW3"},"geometry":{"type":"Point","coordinates":[-10099794.7606921,5955141.89859458]}},{"id":"678","type":"Feature","properties":{"name":"NDBC Buoy Station PNGW3"},"geometry":{"type":"Point","coordinates":[-10173042.9856341,5908189.01860585]}}]}